{
    "pole_position": {
        "pole_sv": {
            "m_pole": "-0.364 ± 0.04",
            "Γ_pole": "-0.0478 ± 0.0023"
        }
    },
    "pole_interpolation": {
        "ppvalues": [
            {
                "m_pole": -1.499974182713777,
                "half_Γ_pole": -0.008511336054652981,
                "invD": 5.125138371361963e-8
            },
            {
                "m_pole": -1.4216978580212403,
                "half_Γ_pole": -0.009815255722332782,
                "invD": 1.1664140222074843e-9
            },
            {
                "m_pole": -1.3432039464875063,
                "half_Γ_pole": -0.010476424579585161,
                "invD": 5.426255981435253e-9
            },
            {
                "m_pole": -1.2649170732687494,
                "half_Γ_pole": -0.01087608136965089,
                "invD": 7.952351598006755e-10
            },
            {
                "m_pole": -1.1862308783903965,
                "half_Γ_pole": -0.011872805314579672,
                "invD": 2.381818573255033e-8
            },
            {
                "m_pole": -1.1080463991611111,
                "half_Γ_pole": -0.01223531416144873,
                "invD": 4.99107312807827e-10
            },
            {
                "m_pole": -1.0297529907269694,
                "half_Γ_pole": -0.012936829816942098,
                "invD": 1.860921342752269e-9
            },
            {
                "m_pole": -0.9511680057958556,
                "half_Γ_pole": -0.01379053086596296,
                "invD": 1.0011859634230503e-9
            },
            {
                "m_pole": -0.8729099405357782,
                "half_Γ_pole": -0.014361295884364772,
                "invD": 1.522406994312623e-8
            },
            {
                "m_pole": -0.7942285250847867,
                "half_Γ_pole": -0.01542138010931297,
                "invD": 2.168413442306253e-8
            },
            {
                "m_pole": -0.7161494237615879,
                "half_Γ_pole": -0.01693658014073183,
                "invD": 4.055917307624298e-9
            },
            {
                "m_pole": -0.6378023980619189,
                "half_Γ_pole": -0.018051153255739753,
                "invD": 2.3068710151150624e-10
            },
            {
                "m_pole": -0.5593519249366047,
                "half_Γ_pole": -0.019364123777045238,
                "invD": 3.3320436212790396e-9
            },
            {
                "m_pole": -0.4811843406291397,
                "half_Γ_pole": -0.020966379945411482,
                "invD": 1.294592220232744e-9
            },
            {
                "m_pole": -0.4028654818354469,
                "half_Γ_pole": -0.02276989034171168,
                "invD": 3.99297919655401e-9
            },
            {
                "m_pole": -0.3247939696437434,
                "half_Γ_pole": -0.02502921644990382,
                "invD": 1.7098840240115007e-10
            },
            {
                "m_pole": -0.24681192267882196,
                "half_Γ_pole": -0.027532046942334427,
                "invD": 7.531741404887701e-10
            },
            {
                "m_pole": -0.16934606734859314,
                "half_Γ_pole": -0.030758820822952608,
                "invD": 5.612234777841012e-9
            },
            {
                "m_pole": -0.09306435061471635,
                "half_Γ_pole": -0.034558241968680375,
                "invD": 1.2052816464463234e-9
            },
            {
                "m_pole": -0.026171253439970323,
                "half_Γ_pole": -0.03934065466967877,
                "invD": 5.484194190232936e-9
            }
        ],
        "mgrid": [
            -1.5,
            -1.421578947368421,
            -1.343157894736842,
            -1.2647368421052632,
            -1.1863157894736842,
            -1.1078947368421053,
            -1.0294736842105263,
            -0.9510526315789474,
            -0.8726315789473684,
            -0.7942105263157895,
            -0.7157894736842105,
            -0.6373684210526316,
            -0.5589473684210526,
            -0.4805263157894737,
            -0.40210526315789474,
            -0.3236842105263158,
            -0.24526315789473685,
            -0.1668421052631579,
            -0.08842105263157894,
            -0.01
        ]
    }
}
